pyats/aereport/__init__.py
pyats/aereport/aerunner.cpython-310-x86_64-linux-gnu.so
pyats/aereport/clean.cpython-310-x86_64-linux-gnu.so
pyats/aereport/client.cpython-310-x86_64-linux-gnu.so
pyats/aereport/clientSection.cpython-310-x86_64-linux-gnu.so
pyats/aereport/clientSubtest.cpython-310-x86_64-linux-gnu.so
pyats/aereport/clientTestcase.cpython-310-x86_64-linux-gnu.so
pyats/aereport/clientTestscript.cpython-310-x86_64-linux-gnu.so
pyats/aereport/easypy_sim.cpython-310-x86_64-linux-gnu.so
pyats/aereport/handlers.cpython-310-x86_64-linux-gnu.so
pyats/aereport/infra.cpython-310-x86_64-linux-gnu.so
pyats/aereport/template.cpython-310-x86_64-linux-gnu.so
pyats/aereport/exceptions/__init__.py
pyats/aereport/exceptions/aereport_errors.cpython-310-x86_64-linux-gnu.so
pyats/aereport/exceptions/utils_errors.cpython-310-x86_64-linux-gnu.so
pyats/aereport/initinfo/__init__.py
pyats/aereport/initinfo/interface.cpython-310-x86_64-linux-gnu.so
pyats/aereport/initinfo/uut.cpython-310-x86_64-linux-gnu.so
pyats/aereport/initinfo/id/__init__.py
pyats/aereport/initinfo/id/idtims.cpython-310-x86_64-linux-gnu.so
pyats/aereport/iou/__init__.py
pyats/aereport/iou/iouinitinfo.cpython-310-x86_64-linux-gnu.so
pyats/aereport/iou/ioulive.cpython-310-x86_64-linux-gnu.so
pyats/aereport/iou/diou/__init__.py
pyats/aereport/iou/diou/ci.cpython-310-x86_64-linux-gnu.so
pyats/aereport/logview/__init__.py
pyats/aereport/logview/logviewmaker.cpython-310-x86_64-linux-gnu.so
pyats/aereport/logview/templates/log_view_template.html
pyats/aereport/logview/templates/styles.css
pyats/aereport/logview/templates/testscript.html
pyats/aereport/logview/templates/teststep.html
pyats/aereport/results/__init__.py
pyats/aereport/results/resultsummary.cpython-310-x86_64-linux-gnu.so
pyats/aereport/results/rollupresult.cpython-310-x86_64-linux-gnu.so
pyats/aereport/results/summary.cpython-310-x86_64-linux-gnu.so
pyats/aereport/runinfo/__init__.py
pyats/aereport/runinfo/abort.cpython-310-x86_64-linux-gnu.so
pyats.aereport-25.9.dist-info/METADATA
pyats.aereport-25.9.dist-info/WHEEL
pyats.aereport-25.9.dist-info/top_level.txt
pyats.aereport-25.9.dist-info/RECORD
